setup.cfg
setup.py
easy_job/__init__.py
easy_job.egg-info/PKG-INFO
easy_job.egg-info/SOURCES.txt
easy_job.egg-info/dependency_links.txt
easy_job.egg-info/requires.txt
easy_job.egg-info/top_level.txt
easy_job/result_backends/__init__.py
easy_job/result_backends/dummy.py
easy_job/result_backends/log.py
easy_job/workers/__init__.py
easy_job/workers/common.py
easy_job/workers/mixins.py
easy_job/workers/mpqueue.py
easy_job/workers/mtqueue.py
easy_job/workers/rabbitmq.py