Metadata-Version: 1.1
Name: easy-job
Version: 0.2.5
Summary: A lightweight background task runner
Home-page: https://github.com/inb-co/easy-job
Author: Mahdi Zareie
Author-email: mahdi.elf@gmail.com
License: UNKNOWN
Keywords: worker,task runner,lightweight job runner
Platform: UNKNOWN
Classifier: Development Status :: 5 - Production/Stable
Classifier: Topic :: Utilities
Classifier: License :: OSI Approved :: BSD License
